Metadata-Version: 2.1
Name: flask-restx-vercel
Version: 1.3.1.dev0
Summary: Fully featured framework for fast, easy and documented API development with Flask
Home-page: https://github.com/Young-Lord/flask-restx-vercel
Author: python-restx Authors
License: BSD-3-Clause
Keywords: flask restx rest api swagger openapi
Classifier: Development Status :: 5 - Production/Stable
Classifier: Programming Language :: Python
Classifier: Environment :: Web Environment
Classifier: Operating System :: OS Independent
Classifier: Intended Audience :: Developers
Classifier: Topic :: System :: Software Distribution
Classifier: Programming Language :: Python
Classifier: Programming Language :: Python :: 3
Classifier: Programming Language :: Python :: 3.8
Classifier: Programming Language :: Python :: 3.9
Classifier: Programming Language :: Python :: 3.10
Classifier: Programming Language :: Python :: 3.11
Classifier: Programming Language :: Python :: 3.12
Classifier: Programming Language :: Python :: Implementation :: PyPy
Classifier: Topic :: Software Development :: Libraries :: Python Modules
Classifier: License :: OSI Approved :: BSD License
Requires-Python: >=3.8
License-File: LICENSE
Requires-Dist: aniso8601 >=0.82
Requires-Dist: jsonschema
Requires-Dist: Flask !=2.0.0,>=0.8
Requires-Dist: werkzeug !=2.0.0
Requires-Dist: pytz
Requires-Dist: importlib-resources
Provides-Extra: dev
Requires-Dist: blinker ; extra == 'dev'
Requires-Dist: Faker ==2.0.0 ; extra == 'dev'
Requires-Dist: mock ==3.0.5 ; extra == 'dev'
Requires-Dist: pytest ==7.0.1 ; extra == 'dev'
Requires-Dist: pytest-benchmark ==3.4.1 ; extra == 'dev'
Requires-Dist: pytest-cov ==4.0.0 ; extra == 'dev'
Requires-Dist: pytest-flask ==1.3.0 ; extra == 'dev'
Requires-Dist: pytest-mock ==3.6.1 ; extra == 'dev'
Requires-Dist: pytest-profiling ==1.7.0 ; extra == 'dev'
Requires-Dist: tzlocal ; extra == 'dev'
Requires-Dist: invoke ==2.2.0 ; extra == 'dev'
Requires-Dist: twine ==3.8.0 ; extra == 'dev'
Requires-Dist: setuptools ; extra == 'dev'
Requires-Dist: tox ; extra == 'dev'
Requires-Dist: black ; extra == 'dev'
Provides-Extra: doc
Requires-Dist: alabaster ==0.7.12 ; extra == 'doc'
Requires-Dist: Sphinx ==5.3.0 ; extra == 'doc'
Requires-Dist: sphinx-issues ==3.0.1 ; extra == 'doc'
Provides-Extra: test
Requires-Dist: blinker ; extra == 'test'
Requires-Dist: Faker ==2.0.0 ; extra == 'test'
Requires-Dist: mock ==3.0.5 ; extra == 'test'
Requires-Dist: pytest ==7.0.1 ; extra == 'test'
Requires-Dist: pytest-benchmark ==3.4.1 ; extra == 'test'
Requires-Dist: pytest-cov ==4.0.0 ; extra == 'test'
Requires-Dist: pytest-flask ==1.3.0 ; extra == 'test'
Requires-Dist: pytest-mock ==3.6.1 ; extra == 'test'
Requires-Dist: pytest-profiling ==1.7.0 ; extra == 'test'
Requires-Dist: tzlocal ; extra == 'test'
Requires-Dist: invoke ==2.2.0 ; extra == 'test'
Requires-Dist: twine ==3.8.0 ; extra == 'test'
Requires-Dist: setuptools ; extra == 'test'
